reddemcee/__init__.py
reddemcee/backend.py
reddemcee/hdf.py
reddemcee/moves.py
reddemcee/reddwrappers.py
reddemcee/sampler.py
reddemcee/state.py
reddemcee/utils.py
reddemcee/utils_legacy.py
reddemcee/wrapper.py
reddemcee-1.0.dist-info/licenses/LICENSE
reddemcee-1.0.dist-info/METADATA
reddemcee-1.0.dist-info/WHEEL
reddemcee-1.0.dist-info/top_level.txt
reddemcee-1.0.dist-info/RECORD
