Metadata-Version: 2.4
Name: reddemcee
Version: 1.0
Summary: Adaptive Parallel Tempering MCMC Ensemble Sampler
Author-email: ReddTea <redd@tea.com>
License: MIT License
Project-URL: Homepage, https://reddemcee.readthedocs.io/
Project-URL: Documentation, https://reddemcee.readthedocs.io/
Project-URL: Repository, https://github.com/ReddTea/reddemcee/
Project-URL: Issues, https://github.com/ReddTea/reddemcee/issues
Keywords: python,MCMC,sampler,adaptive,parallel tempering
Classifier: Programming Language :: Python :: 3
Classifier: License :: OSI Approved :: MIT License
Classifier: Operating System :: OS Independent
Requires-Python: >=3.6
License-File: LICENSE
Requires-Dist: numpy
Requires-Dist: emcee>=3
Requires-Dist: tqdm
Requires-Dist: scipy
Dynamic: license-file
